[
    {
        "actRewardShow": 980015,
        "chapterId": 102,
        "difficulty": 1,
        "firstAreaID": 2405,
        "MaxAvatarNumberPerArea": 3,
        "recCombatNum": 500,
        "rewardPreview": 980015,
        "unlockTeamLv": 20,
        "difficultyText": {
            "hash": 1721973960
        },
        "difficultyUnlockText": {
            "hash": -2044522980
        },
        "recGroupText": {
            "hash": -1614060369
        },
        "areaList": [
            2405
        ],
        "recTeamLv": [
            20,
            30
        ]
    },
    {
        "actRewardShow": 980015,
        "chapterId": 104,
        "difficulty": 1,
        "firstAreaID": 2415,
        "MaxAvatarNumberPerArea": 3,
        "recCombatNum": 500,
        "rewardPreview": 980015,
        "unlockTeamLv": 20,
        "difficultyText": {
            "hash": 1722033542
        },
        "difficultyUnlockText": {
            "hash": -2044522978
        },
        "recGroupText": {
            "hash": -1614060369
        },
        "areaList": [
            2415
        ],
        "recTeamLv": [
            20,
            30
        ]
    },
    {
        "actRewardShow": 980015,
        "chapterId": 106,
        "difficulty": 1,
        "firstAreaID": 2425,
        "MaxAvatarNumberPerArea": 3,
        "recCombatNum": 500,
        "rewardPreview": 980015,
        "unlockTeamLv": 20,
        "difficultyText": {
            "hash": 1722093124
        },
        "difficultyUnlockText": {
            "hash": -2044522976
        },
        "recGroupText": {
            "hash": -1614060369
        },
        "areaList": [
            2425
        ],
        "recTeamLv": [
            20,
            30
        ]
    },
    {
        "actRewardShow": 980015,
        "chapterId": 108,
        "difficulty": 1,
        "firstAreaID": 2441,
        "MaxAvatarNumberPerArea": 3,
        "recCombatNum": 500,
        "rewardPreview": 980015,
        "unlockTeamLv": 20,
        "difficultyText": {
            "hash": 1722152706
        },
        "difficultyUnlockText": {
            "hash": -2044522974
        },
        "recGroupText": {
            "hash": -1614060369
        },
        "areaList": [
            2441
        ],
        "recTeamLv": [
            20,
            30
        ]
    },
    {
        "actRewardShow": 980015,
        "chapterId": 110,
        "difficulty": 1,
        "firstAreaID": 2461,
        "MaxAvatarNumberPerArea": 3,
        "recCombatNum": 500,
        "rewardPreview": 980015,
        "unlockTeamLv": 20,
        "difficultyText": {
            "hash": 1722837899
        },
        "difficultyUnlockText": {
            "hash": -2044522951
        },
        "recGroupText": {
            "hash": -1614060369
        },
        "areaList": [
            2461
        ],
        "recTeamLv": [
            20,
            30
        ]
    },
    {
        "actRewardShow": 980015,
        "chapterId": 112,
        "difficulty": 1,
        "firstAreaID": 2481,
        "MaxAvatarNumberPerArea": 3,
        "recCombatNum": 500,
        "rewardPreview": 980015,
        "unlockTeamLv": 20,
        "difficultyText": {
            "hash": 1722897481
        },
        "difficultyUnlockText": {
            "hash": -2044522949
        },
        "recGroupText": {
            "hash": -1614060369
        },
        "areaList": [
            2481
        ],
        "recTeamLv": [
            20,
            30
        ]
    },
    {
        "actRewardShow": 980015,
        "chapterId": 114,
        "difficulty": 1,
        "firstAreaID": 2501,
        "MaxAvatarNumberPerArea": 3,
        "recCombatNum": 500,
        "rewardPreview": 980015,
        "unlockTeamLv": 20,
        "difficultyText": {
            "hash": 1722897481
        },
        "difficultyUnlockText": {
            "hash": -2044522949
        },
        "recGroupText": {
            "hash": -1614060369
        },
        "areaList": [
            2501
        ],
        "recTeamLv": [
            20,
            30
        ]
    }
]