[
    {
        "MemoryID": 1001,
        "MemoryName": {
            "hash": 767531436
        },
        "MemoryText": {
            "hash": -2076687538
        },
        "MemoryImage": "event/Immediately/Reburn/PicAlbum"
    },
    {
        "MemoryID": 1002,
        "MemoryName": {
            "hash": 767531437
        },
        "MemoryText": {
            "hash": -2076687537
        },
        "MemoryImage": "event/Immediately/Reburn/PicAlbum2"
    },
    {
        "MemoryID": 1003,
        "MemoryName": {
            "hash": 767531438
        },
        "MemoryText": {
            "hash": -2076687536
        },
        "MemoryImage": "event/Immediately/Reburn/PicAlbum3"
    }
]