[
    {
        "ActivityID": 1,
        "CatalogID": 1,
        "Author": "WikiActivityCatalog_Author_1",
        "AuthorPic": "SpriteOutput/PhoneStrapIcon/WikiAcitivityKiana",
        "Description": "WikiActivityCatalog_Description_1",
        "Title": "WikiActivityCatalog_Title_1"
    },
    {
        "ActivityID": 2,
        "CatalogID": 2,
        "Author": "WikiActivityCatalog_Author_2",
        "AuthorPic": "SpriteOutput/PhoneStrapIcon/Winter2018Collection_Bronya",
        "Description": "WikiActivityCatalog_Description_2",
        "Title": "WikiActivityCatalog_Title_2"
    },
    {
        "ActivityID": 3,
        "CatalogID": 3,
        "Author": "WikiActivityCatalog_Author_3",
        "AuthorPic": "SpriteOutput/CityEvent/CityEventChibiFigures/SummerAvatarKiana",
        "Description": "WikiActivityCatalog_Description_3",
        "Title": "WikiActivityCatalog_Title_3"
    },
    {
        "ActivityID": 4,
        "CatalogID": 4,
        "Author": "WikiActivityCatalog_Author_4",
        "AuthorPic": "SpriteOutput/PhoneStrapIcon/WikiCollectionCover_Dress",
        "Description": "WikiActivityCatalog_Description_4",
        "Title": "WikiActivityCatalog_Title_4"
    }
]